geotite/__init__.py
geotite-0.0.1.dist-info/METADATA
geotite-0.0.1.dist-info/WHEEL
geotite-0.0.1.dist-info/top_level.txt
geotite-0.0.1.dist-info/RECORD
